queued_storage/__init__.py
queued_storage/backends.py
queued_storage/conf.py
queued_storage/fields.py
queued_storage/models.py
queued_storage/signals.py
queued_storage/tasks.py
queued_storage/utils.py
django_queued_storage-0.8.0.dist-info/top_level.txt
django_queued_storage-0.8.0.dist-info/METADATA
django_queued_storage-0.8.0.dist-info/DESCRIPTION.rst
django_queued_storage-0.8.0.dist-info/metadata.json
django_queued_storage-0.8.0.dist-info/WHEEL
django_queued_storage-0.8.0.dist-info/RECORD
