Metadata-Version: 1.1
Name: django-queued-storage
Version: 0.8.0
Summary: Queued remote storage for Django.
Home-page: https://github.com/jazzband/django-queued-storage
Author: Jannis Leidel
Author-email: jannis@leidel.info
License: BSD
Platform: UNKNOWN
Classifier: Development Status :: 4 - Beta
Classifier: Framework :: Django
Classifier: Intended Audience :: Developers
Classifier: License :: OSI Approved :: BSD License
Classifier: Operating System :: OS Independent
Classifier: Programming Language :: Python
Classifier: Programming Language :: Python :: 2.7
Classifier: Programming Language :: Python :: 3.3
Classifier: Programming Language :: Python :: 3.4
Classifier: Topic :: Utilities
